tighterhoeffding/__init__.py
tighterhoeffding-1.0.dist-info/LICENSE
tighterhoeffding-1.0.dist-info/METADATA
tighterhoeffding-1.0.dist-info/WHEEL
tighterhoeffding-1.0.dist-info/top_level.txt
tighterhoeffding-1.0.dist-info/RECORD
